action_template/__init__.py
action_template/__main__.py
action_template/main.py
re_action_template-2.1.3.dist-info/LICENSE
re_action_template-2.1.3.dist-info/METADATA
re_action_template-2.1.3.dist-info/WHEEL
re_action_template-2.1.3.dist-info/entry_points.txt
re_action_template-2.1.3.dist-info/RECORD
