Metadata-Version: 2.1
Name: re-action-template
Version: 2.1.3
Summary: 
License: SSPL-1.0
Author: Philipp Gayret
Author-email: philipp@release-engineers.com
Requires-Python: >=3.11,<4.0
Classifier: License :: Other/Proprietary License
Classifier: Programming Language :: Python :: 3
Classifier: Programming Language :: Python :: 3.11
Requires-Dist: Markdown (>=3.3.6,<4.0.0)
Requires-Dist: fire (>=0.5.0,<0.6.0)
Requires-Dist: jinja2 (>=3.0.3,<4.0.0)
Requires-Dist: pyyaml (>=6.0,<7.0)
